csms/__init__.py
csms/functions.py
csms/services.py
huaweicloud_csms_environ-0.1.2.dist-info/LICENSE
huaweicloud_csms_environ-0.1.2.dist-info/WHEEL
huaweicloud_csms_environ-0.1.2.dist-info/METADATA
huaweicloud_csms_environ-0.1.2.dist-info/RECORD
