Metadata-Version: 2.1
Name: huaweicloud-csms-environ
Version: 0.1.2
Summary: 
Home-page: https://github.com/C0D1UM/huaweicloud-csms-environ
License: MIT
Keywords: huaweicloud,csms,environment-variables
Author: CODIUM
Author-email: support@codium.co
Requires-Python: >=3.8,<4.0
Classifier: License :: OSI Approved :: MIT License
Classifier: Programming Language :: Python :: 3
Classifier: Programming Language :: Python :: 3.8
Classifier: Programming Language :: Python :: 3.9
Classifier: Programming Language :: Python :: 3.10
Classifier: Programming Language :: Python :: 3.11
Requires-Dist: huaweicloudsdkcsms (>=3.1.0,<4.0.0)
Project-URL: Repository, https://github.com/C0D1UM/huaweicloud-csms-environ
